polynom/__init__.py
polynom/_base.py
polynom/chebyshev.py
polynom/gegenbauer.py
polynom/lagrange.py
polynom/legendre.py
polynom/monomial.py
polynom/newton.py
polynom/shared.py
polynom-0.0.3.dist-info/LICENSE
polynom-0.0.3.dist-info/METADATA
polynom-0.0.3.dist-info/WHEEL
polynom-0.0.3.dist-info/top_level.txt
polynom-0.0.3.dist-info/RECORD
